odoo10_addon_barcodes_generator_lot-10.0.1.0.0-py2.7-nspkg.pth
odoo/addons/barcodes_generator_lot/README.rst
odoo/addons/barcodes_generator_lot/__init__.py
odoo/addons/barcodes_generator_lot/__manifest__.py
odoo/addons/barcodes_generator_lot/demo/barcode_rule.xml
odoo/addons/barcodes_generator_lot/demo/function.xml
odoo/addons/barcodes_generator_lot/demo/ir_sequence.xml
odoo/addons/barcodes_generator_lot/demo/stock_production_lot.xml
odoo/addons/barcodes_generator_lot/models/__init__.py
odoo/addons/barcodes_generator_lot/models/barcode_rule.py
odoo/addons/barcodes_generator_lot/models/stock_production_lot.py
odoo/addons/barcodes_generator_lot/static/description/icon.png
odoo/addons/barcodes_generator_lot/static/description/icon.svg
odoo/addons/barcodes_generator_lot/static/description/stock_production_lot_sequence_generation.png
odoo/addons/barcodes_generator_lot/tests/__init__.py
odoo/addons/barcodes_generator_lot/tests/test_barcode_generator.py
odoo/addons/barcodes_generator_lot/views/stock_production_lot.xml
odoo10_addon_barcodes_generator_lot-10.0.1.0.0.dist-info/DESCRIPTION.rst
odoo10_addon_barcodes_generator_lot-10.0.1.0.0.dist-info/METADATA
odoo10_addon_barcodes_generator_lot-10.0.1.0.0.dist-info/RECORD
odoo10_addon_barcodes_generator_lot-10.0.1.0.0.dist-info/WHEEL
odoo10_addon_barcodes_generator_lot-10.0.1.0.0.dist-info/metadata.json
odoo10_addon_barcodes_generator_lot-10.0.1.0.0.dist-info/namespace_packages.txt
odoo10_addon_barcodes_generator_lot-10.0.1.0.0.dist-info/top_level.txt
